chainopy-1.0.3.dist-info/RECORD
chainopy-1.0.3.dist-info/WHEEL
chainopy-1.0.3.dist-info/LICENSE
chainopy-1.0.3.dist-info/top_level.txt
chainopy-1.0.3.dist-info/METADATA
chainopy/markov_chain.py
chainopy/_exceptions.py
chainopy/nn.py
chainopy/_visualizations.py
chainopy/_caching.py
chainopy/_fileio.py
chainopy/__init__.py
chainopy/markov_switching.py
chainopy/_backend/_learn_matrix.pyx
chainopy/_backend/_learn_matrix.cpython-311-x86_64-linux-gnu.so
chainopy/_backend/_simulate.pyx
chainopy/_backend/_absorbing.pyx
chainopy/_backend/_simulate.cpython-311-x86_64-linux-gnu.so
chainopy/_backend/_is_communicating.pyx
chainopy/_backend/__init__.py
chainopy/_backend/_is_communicating.cpython-311-x86_64-linux-gnu.so
chainopy/_backend/_stationary_dist.cpython-311-x86_64-linux-gnu.so
chainopy/_backend/_absorbing.cpython-311-x86_64-linux-gnu.so
chainopy/_backend/_stationary_dist.pyx
chainopy/tests/test_nn.py
chainopy/tests/__init__.py
chainopy/tests/test_markovchain.py
chainopy/tests/test_switching.py
