Metadata-Version: 2.1
Name: chainopy
Version: 1.0.3
Summary: A Python Library for Markov Chain based Stochastic Analysis!
Home-page: https://github.com/aadya940/chainopy
Author: Aadya Aneesh Chinubhai
Author-email: Aadya Aneesh Chinubhai <aadyachinubhai@gmail.com>
License: Copyright 2024 Aadya Chinubhai
Project-URL: homepage, https://chainopy.readthedocs.io/en/latest/
Project-URL: repository, https://github.com/aadya940/chainopy
Keywords: markov chain,stochastic analysis,python
Requires-Python: >=3.10
License-File: LICENSE
Requires-Dist: numpy==2.0.0
Requires-Dist: Cython>=3.0.4
Requires-Dist: scipy>=1.13.0
Requires-Dist: xarray>=2024.06.0
Requires-Dist: matplotlib>=3.8.4
Requires-Dist: networkx==3.3
Requires-Dist: torch>=2.3.0
Requires-Dist: statsmodels>=0.14.2
